djangomix/__init__.py
djangomix/templatetags/__init__.py
djangomix/templatetags/mix.py
djangomix-1.1.3.dist-info/LICENSE
djangomix-1.1.3.dist-info/METADATA
djangomix-1.1.3.dist-info/WHEEL
djangomix-1.1.3.dist-info/top_level.txt
djangomix-1.1.3.dist-info/RECORD
