Metadata-Version: 2.1
Name: djangomix
Version: 1.1.3
Summary: Django integration for Laravel Mix
Home-page: https://github.com/m-a-k-o/django-mix
Author: Marek Racik
Author-email: marek@idea-loop.com
License: UNKNOWN
Keywords: Django Mix
Platform: UNKNOWN
Classifier: Development Status :: 5 - Production/Stable
Classifier: Environment :: Web Environment
Classifier: Framework :: Django
Classifier: Intended Audience :: Developers
Classifier: Programming Language :: Python
Classifier: Topic :: Software Development :: Libraries :: Python Modules
Requires: Django (>=1.11)
Requires-Dist: Django (>=1.11)
